{"id":"sympy.vector.coordsysrect","path":"/home/thiago/Sync/projects/work/pySymmPol/.venv/lib/python3.12/site-packages/sympy/vector/coordsysrect.py","mtime":1715339793,"size":36859,"hash":"d49578181806f7d24a216a36b2760c32020909da1bdd773062aabdb3c77a7c0f","data_mtime":1715208976,"dependencies":["sympy.functions.elementary.miscellaneous","sympy.functions.elementary.trigonometric","sympy.core.basic","sympy.core.cache","sympy.core.symbol","sympy.matrices.immutable","sympy.matrices.matrices","sympy.vector.scalar","sympy.core.containers","sympy.core.function","sympy.matrices.dense","sympy.simplify.simplify","sympy.simplify.trigsimp","sympy.vector.orienters","sympy.vector.functions","sympy.vector.vector","collections.abc","sympy.core","sympy.solvers","sympy.vector","sympy","builtins","pyexpat.errors","pyexpat.model","_collections_abc","abc","sympy.core._print_helpers","sympy.core.core","sympy.core.evalf","sympy.core.expr","sympy.core.singleton","sympy.logic","sympy.logic.boolalg","sympy.matrices","sympy.matrices.common","sympy.matrices.expressions","sympy.matrices.expressions.matexpr","sympy.matrices.repmatrix","sympy.solvers.solvers","sympy.vector.basisdependent","sympy.vector.point","typing"],"suppressed":[],"options":{"allow_untyped_globals":false,"disable_memoryview_promotion":false,"strict_equality":false,"disallow_any_explicit":false,"platform":"linux","always_true":[],"disable_bytearray_promotion":false,"disallow_untyped_calls":false,"warn_unreachable":false,"disallow_any_generics":false,"always_false":[],"disable_error_code":[],"strict_concatenate":false,"disabled_error_codes":[],"disallow_subclassing_any":false,"bazel":false,"ignore_errors":false,"disallow_any_unimported":false,"strict_optional":true,"disallow_any_expr":false,"disallow_untyped_decorators":false,"warn_return_any":false,"warn_unused_ignores":false,"enabled_error_codes":[],"local_partial_types":false,"ignore_missing_imports":false,"implicit_reexport":true,"implicit_optional":false,"old_type_inference":false,"disallow_incomplete_defs":false,"follow_imports":"normal","allow_redefinition":false,"mypyc":false,"plugins":[],"enable_error_code":[],"check_untyped_defs":false,"disallow_any_decorated":false,"warn_no_return":true,"extra_checks":false,"disallow_untyped_defs":false,"follow_imports_for_stubs":false},"dep_prios":[5,5,5,5,5,5,5,5,5,5,5,5,5,5,20,5,5,5,5,10,20,5,20,20,30,30,30,30,30,30,30,30,30,30,30,30,30,30,30,30,30,30],"dep_lines":[14,15,3,4,6,8,9,11,12,13,16,18,19,21,506,1034,1,5,10,20,20,1,1,1,1,1,1,1,1,1,1,1,1,1,1,1,1,1,1,1,1,1],"interface_hash":"6acf27c563c1fcd6bb630b326341825985c07c3667e633b5126715bc6bca7aba","version_id":"1.10.0","ignore_all":true,"plugin_data":null}